fetch/__init__.py
fetch/const.py
fetch/fetch.py
at_fetch-0.1.3.dist-info/METADATA
at_fetch-0.1.3.dist-info/WHEEL
at_fetch-0.1.3.dist-info/RECORD
