Metadata-Version: 2.1
Name: at-fetch
Version: 0.1.3
Summary: 
License: MIT
Author: thecatshidog
Requires-Python: >=3.8
Classifier: License :: OSI Approved :: MIT License
Classifier: Programming Language :: Python :: 3
Classifier: Programming Language :: Python :: 3.8
Classifier: Programming Language :: Python :: 3.9
Classifier: Programming Language :: Python :: 3.10
Classifier: Programming Language :: Python :: 3.11
Requires-Dist: httpx[http2] (>=0.24.0,<0.25.0)
Requires-Dist: pandas (>=2.0.1,<3.0.0)
